aksquare/__init__.py
aksquare/data.py
aksquare/layers.py
aksquare/loss.py
aksquare/nn.py
aksquare/optim.py
aksquare/tensor.py
aksquare/train.py
aksquare-0.0.1.dist-info/LICENSE
aksquare-0.0.1.dist-info/METADATA
aksquare-0.0.1.dist-info/WHEEL
aksquare-0.0.1.dist-info/top_level.txt
aksquare-0.0.1.dist-info/RECORD
