Metadata-Version: 2.1
Name: aksquare
Version: 0.0.1
Summary: Yet another simple deep learning library
Home-page: https://github.com/scoopml/aksquare
Author: Harish S.G
Author-email: harishsg99@gmail.com
License: MIT
Download-URL: https://pypi.org/project/aksquare/
Keywords: ak,square,aksquare
Platform: UNKNOWN
Requires-Dist: numpy
